[
  {
    "region": 12851,
    "name": "Autumn Voyage",
    "song": 2,
    "frame": 39533,
    "button": 154109
  },
  {
    "region": 12593,
    "name": "Book Of Spells",
    "song": 64,
    "frame": 39564,
    "button": 154140
  },
  {
    "region": 12850,
    "name": "Harmony",
    "song": 76,
    "frame": 39774,
    "button": 155094
  },
  {
    "region": 12184,
    "name": "Cave Background",
    "song": 325,
    "frame": 39580,
    "button": 154156
  },
  {
    "region": 12185,
    "name": "Cave Background",
    "song": 325,
    "frame": 39580,
    "button": 154156
  },
  {
    "region": 12183,
    "name": "Cave Background",
    "song": 325,
    "frame": 39580,
    "button": 154156
  },
  {
    "region": 11929,
    "name": "Cave Background",
    "song": 325,
    "frame": 39580,
    "button": 154156
  }
]